mmpdblib/__init__.py
mmpdblib/__main__.py
mmpdblib/analysis_algorithms.py
mmpdblib/cansmirks_table.py
mmpdblib/config.py
mmpdblib/create_index.sql
mmpdblib/dbutils.py
mmpdblib/drop_index.sql
mmpdblib/environment.py
mmpdblib/fileio.py
mmpdblib/fragment_algorithm.py
mmpdblib/fragment_create_index.sql
mmpdblib/fragment_db.py
mmpdblib/fragment_records.py
mmpdblib/fragment_schema.sql
mmpdblib/fragment_types.py
mmpdblib/index_algorithm.py
mmpdblib/index_types.py
mmpdblib/index_writers.py
mmpdblib/properties_io.py
mmpdblib/reporters.py
mmpdblib/rgroup2smarts.py
mmpdblib/schema.py
mmpdblib/schema.sql
mmpdblib/smarts_aliases.py
mmpdblib/smiles_syntax.py
mmpdblib/cli/__init__.py
mmpdblib/cli/click_utils.py
mmpdblib/cli/create_index.py
mmpdblib/cli/drop_index.py
mmpdblib/cli/fragdb_constants.py
mmpdblib/cli/fragdb_list.py
mmpdblib/cli/fragdb_merge.py
mmpdblib/cli/fragdb_partition.py
mmpdblib/cli/fragment.py
mmpdblib/cli/fragment_click.py
mmpdblib/cli/generate.py
mmpdblib/cli/help_.py
mmpdblib/cli/index.py
mmpdblib/cli/list_.py
mmpdblib/cli/loadprops.py
mmpdblib/cli/merge.py
mmpdblib/cli/predict.py
mmpdblib/cli/propcat.py
mmpdblib/cli/proprulecat.py
mmpdblib/cli/rgroup2smarts.py
mmpdblib/cli/rulecat.py
mmpdblib/cli/ruleenvcat.py
mmpdblib/cli/smi_split.py
mmpdblib/cli/smi_utils.py
mmpdblib/cli/smicat.py
mmpdblib/cli/smifrag.py
mmpdblib/cli/transform.py
mmpdb-3.1.4.dist-info/METADATA
mmpdb-3.1.4.dist-info/WHEEL
mmpdb-3.1.4.dist-info/entry_points.txt
mmpdb-3.1.4.dist-info/licenses/LICENSE.txt
mmpdb-3.1.4.dist-info/RECORD
