Metadata-Version: 2.4
Name: mmpdb
Version: 3.1.4
Summary: A package to identify matched molecular pairs and use them to predict property changes
Project-URL: Homepage, https://github.com/rdkit/mmpdb
Author-email: Andrew Dalke <dalke@dalkescientific.com>
Maintainer-email: "Jerome (chem-bio)" <rdkit-discuss@lists.sourceforge.net>, Christian Kramer <rdkit-discuss@lists.sourceforge.net>
License-File: LICENSE.txt
Keywords: MMP,cheminformatics,matched molecular pair
Classifier: Development Status :: 5 - Production/Stable
Classifier: Environment :: Console
Classifier: Intended Audience :: Science/Research
Classifier: Operating System :: Unix
Classifier: Programming Language :: Python :: 3
Classifier: Topic :: Scientific/Engineering :: Chemistry
Requires-Python: >=3.10
Requires-Dist: click>=8.2
Requires-Dist: peewee>=3.0
Requires-Dist: rdkit>=2024.3
Requires-Dist: scipy
